xmltodict.py
xmltodict-1.0.1.dist-info/licenses/LICENSE
xmltodict-1.0.1.dist-info/METADATA
xmltodict-1.0.1.dist-info/WHEEL
xmltodict-1.0.1.dist-info/top_level.txt
xmltodict-1.0.1.dist-info/RECORD
